holiday_narrative_parser/__init__.py
holiday_narrative_parser/main.py
holiday_narrative_parser/prompts.py
holiday_narrative_parser-2025.12.22105725.dist-info/METADATA
holiday_narrative_parser-2025.12.22105725.dist-info/WHEEL
holiday_narrative_parser-2025.12.22105725.dist-info/top_level.txt
holiday_narrative_parser-2025.12.22105725.dist-info/RECORD
