Metadata-Version: 2.4
Name: holiday-narrative-parser
Version: 2025.12.22105725
Summary: holiday-narrative-parser processes holiday event narratives to extract themes, tone, and key details for analysis and summarization.
Author-email: holiday-narrative-parser <hi@eugene.plus>
License: MIT
Project-URL: Homepage, https://github.com/chigwell/holiday-narrative-parser
Requires-Python: >=3.9
Requires-Dist: langchain-llm7>=0.0.0
Requires-Dist: llmatch-messages>=0.0.0
Requires-Dist: langchain-core>=0.3.0
